PythonFastAPIWrapper/__init__.py
PythonFastAPIWrapper/api.py
PythonFastAPIWrapper/crud.py
PythonFastAPIWrapper/wrapper.py
thomasbaumkircher_fastapi-1.0.0.dist-info/METADATA
thomasbaumkircher_fastapi-1.0.0.dist-info/WHEEL
thomasbaumkircher_fastapi-1.0.0.dist-info/top_level.txt
thomasbaumkircher_fastapi-1.0.0.dist-info/RECORD
