Metadata-Version: 2.1
Name: thomasbaumkircher_fastapi
Version: 1.0.0
Summary: A reusable CRUD Interface for FastAPI
Home-page: https://github.com/Thomas/my_library
Author: Thomas Baumkircher
Author-email: thomasbaumkircher@gmail.com
